{
  "name": "克雷莫纳",
  "league": "serie_a",
  "players": [
    {
      "name": "费德里科·博纳佐利",
      "english_name": "Federico Bonazzoli",
      "position": "前锋",
      "age": 0,
      "nationality": "",
      "transfer_status": "current",
      "join_date": "",
      "contract_until": "",
      "market_value": 0,
      "stats": {
        "appearances": 32,
        "minutes": 2329,
        "goals": 8,
        "assists": 1,
        "yellow_cards": 3,
        "red_cards": 0
      },
      "shooting_stats": {
        "source": "understat",
        "shots": 70,
        "goals": 8,
        "xg": 7.651005818974227,
        "npxg": 6.128408163320273,
        "xg_chain": 9.47975029842928,
        "xg_buildup": 3.6543022310361266
      },
      "passing_stats": {
        "source": "understat",
        "key_passes": 13,
        "xa": 1.532783793285489
      },
      "advanced_stats": {
        "source": "understat",
        "games": 32,
        "minutes": 2329,
        "position_code": "F S",
        "xg": 7.651005818974227,
        "xa": 1.532783793285489,
        "npxg": 6.128408163320273,
        "shots": 70,
        "key_passes": 13,
        "xg_chain": 9.47975029842928,
        "xg_buildup": 3.6543022310361266
      },
      "data_sources": [
        "sofascore.com",
        "understat.com"
      ],
      "understat_player_id": "2019",
      "heatmap": {
        "source": "understat_shots",
        "grid_rows": 5,
        "grid_cols": 6,
        "shot_count": 265,
        "shot_density": [
          [
            0,
            0,
            0,
            0,
            0,
            0
          ],
          [
            0,
            0,
            0,
            0,
            30,
            40
          ],
          [
            0,
            0,
            0,
            1,
            55,
            99
          ],
          [
            0,
            0,
            0,
            1,
            14,
            23
          ],
          [
            0,
            0,
            0,
            0,
            1,
            1
          ]
        ]
      },
      "shot_map_available": true,
      "wikidata_id": "Q16382834",
      "name_cn_source": "wikidata",
      "sofascore_player_id": 284363,
      "shirt_number": 90,
      "shirt_number_source": "sofascore"
    },
    {
      "name": "傑米·瓦迪",
      "english_name": "Jamie Vardy",
      "position": "前锋",
      "age": 0,
      "nationality": "",
      "transfer_status": "current",
      "join_date": "",
      "contract_until": "",
      "market_value": 0,
      "stats": {
        "appearances": 26,
        "minutes": 1867,
        "goals": 5,
        "assists": 2,
        "yellow_cards": 4,
        "red_cards": 0
      },
      "shooting_stats": {
        "source": "understat",
        "shots": 28,
        "goals": 5,
        "xg": 5.699792170897126,
        "npxg": 5.699792170897126,
        "xg_chain": 9.164527025073767,
        "xg_buildup": 2.2362013272941113
      },
      "passing_stats": {
        "source": "understat",
        "key_passes": 15,
        "xa": 2.123625386506319
      },
      "advanced_stats": {
        "source": "understat",
        "games": 26,
        "minutes": 1867,
        "position_code": "F S",
        "xg": 5.699792170897126,
        "xa": 2.123625386506319,
        "npxg": 5.699792170897126,
        "shots": 28,
        "key_passes": 15,
        "xg_chain": 9.164527025073767,
        "xg_buildup": 2.2362013272941113
      },
      "data_sources": [
        "sofascore.com",
        "understat.com"
      ],
      "understat_player_id": "755",
      "heatmap": {
        "source": "understat_shots",
        "grid_rows": 5,
        "grid_cols": 6,
        "shot_count": 705,
        "shot_density": [
          [
            0,
            0,
            0,
            0,
            1,
            3
          ],
          [
            0,
            0,
            0,
            1,
            17,
            112
          ],
          [
            1,
            0,
            0,
            1,
            37,
            360
          ],
          [
            0,
            0,
            0,
            0,
            19,
            150
          ],
          [
            0,
            0,
            0,
            1,
            0,
            2
          ]
        ]
      },
      "shot_map_available": true,
      "wikidata_id": "Q6147586",
      "name_cn_source": "wikidata",
      "sofascore_player_id": 173827,
      "shirt_number": 10,
      "shirt_number_source": "sofascore"
    },
    {
      "name": "Filippo Terracciano",
      "english_name": "Filippo Terracciano",
      "position": "后卫",
      "age": 0,
      "nationality": "",
      "transfer_status": "current",
      "join_date": "",
      "contract_until": "",
      "market_value": 0,
      "stats": {
        "appearances": 33,
        "minutes": 2755,
        "goals": 2,
        "assists": 0,
        "yellow_cards": 6,
        "red_cards": 0
      },
      "shooting_stats": {
        "source": "understat",
        "shots": 14,
        "goals": 2,
        "xg": 2.3331454526633024,
        "npxg": 2.3331454526633024,
        "xg_chain": 4.054625009186566,
        "xg_buildup": 3.587072870694101
      },
      "passing_stats": {
        "source": "understat",
        "key_passes": 10,
        "xa": 0.5284051159396768
      },
      "advanced_stats": {
        "source": "understat",
        "games": 33,
        "minutes": 2755,
        "position_code": "D S",
        "xg": 2.3331454526633024,
        "xa": 0.5284051159396768,
        "npxg": 2.3331454526633024,
        "shots": 14,
        "key_passes": 10,
        "xg_chain": 4.054625009186566,
        "xg_buildup": 3.587072870694101
      },
      "data_sources": [
        "sofascore.com",
        "understat.com"
      ],
      "understat_player_id": "8512",
      "heatmap": {
        "source": "understat_shots",
        "grid_rows": 5,
        "grid_cols": 6,
        "shot_count": 31,
        "shot_density": [
          [
            0,
            0,
            0,
            1,
            0,
            0
          ],
          [
            0,
            0,
            0,
            0,
            6,
            3
          ],
          [
            1,
            0,
            0,
            0,
            4,
            10
          ],
          [
            0,
            0,
            0,
            0,
            2,
            4
          ],
          [
            0,
            0,
            0,
            0,
            0,
            0
          ]
        ]
      },
      "shot_map_available": true,
      "wikidata_id": "Q110137666",
      "name_cn_source": "wikidata",
      "sofascore_player_id": 1034303,
      "shirt_number": 24,
      "shirt_number_source": "sofascore"
    },
    {
      "name": "费德里科·巴斯奇罗托",
      "english_name": "Federico Baschirotto",
      "position": "后卫",
      "age": 0,
      "nationality": "",
      "transfer_status": "current",
      "join_date": "",
      "contract_until": "",
      "market_value": 0,
      "stats": {
        "appearances": 29,
        "minutes": 2540,
        "goals": 2,
        "assists": 0,
        "yellow_cards": 2,
        "red_cards": 0
      },
      "shooting_stats": {
        "source": "understat",
        "shots": 12,
        "goals": 2,
        "xg": 1.1395598910748959,
        "npxg": 1.1395598910748959,
        "xg_chain": 1.8369396440684795,
        "xg_buildup": 1.706673014909029
      },
      "passing_stats": {
        "source": "understat",
        "key_passes": 2,
        "xa": 0.07074637897312641
      },
      "advanced_stats": {
        "source": "understat",
        "games": 29,
        "minutes": 2540,
        "position_code": "D",
        "xg": 1.1395598910748959,
        "xa": 0.07074637897312641,
        "npxg": 1.1395598910748959,
        "shots": 12,
        "key_passes": 2,
        "xg_chain": 1.8369396440684795,
        "xg_buildup": 1.706673014909029
      },
      "data_sources": [
        "sofascore.com",
        "understat.com"
      ],
      "understat_player_id": "10902",
      "heatmap": {
        "source": "understat_shots",
        "grid_rows": 5,
        "grid_cols": 6,
        "shot_count": 73,
        "shot_density": [
          [
            0,
            0,
            0,
            0,
            0,
            0
          ],
          [
            0,
            0,
            0,
            0,
            3,
            3
          ],
          [
            0,
            0,
            0,
            0,
            1,
            63
          ],
          [
            0,
            0,
            0,
            0,
            0,
            3
          ],
          [
            0,
            0,
            0,
            0,
            0,
            0
          ]
        ]
      },
      "shot_map_available": true,
      "wikidata_id": "Q42433448",
      "name_cn_source": "wikidata",
      "sofascore_player_id": 786175,
      "shirt_number": 6,
      "shirt_number_source": "sofascore"
    },
    {
      "name": "曼努埃爾·德·盧卡",
      "english_name": "Manuel De Luca",
      "position": "",
      "age": 0,
      "nationality": "",
      "transfer_status": "current",
      "join_date": "",
      "contract_until": "",
      "market_value": 0,
      "stats": {
        "appearances": 2,
        "minutes": 10,
        "goals": 1,
        "assists": 0,
        "yellow_cards": 0,
        "red_cards": 0
      },
      "shooting_stats": {
        "source": "understat",
        "shots": 2,
        "goals": 1,
        "xg": 0.835056483745575,
        "npxg": 0.07375766336917877,
        "xg_chain": 0.07375766336917877,
        "xg_buildup": 0.0
      },
      "passing_stats": {
        "source": "understat",
        "key_passes": 0,
        "xa": 0.0
      },
      "advanced_stats": {
        "source": "understat",
        "games": 2,
        "minutes": 10,
        "position_code": "S",
        "xg": 0.835056483745575,
        "xa": 0.0,
        "npxg": 0.07375766336917877,
        "shots": 2,
        "key_passes": 0,
        "xg_chain": 0.07375766336917877,
        "xg_buildup": 0.0
      },
      "data_sources": [
        "understat.com"
      ],
      "understat_player_id": "1598",
      "heatmap": {
        "source": "understat_shots",
        "grid_rows": 5,
        "grid_cols": 6,
        "shot_count": 2,
        "shot_density": [
          [
            0,
            0,
            0,
            0,
            0,
            0
          ],
          [
            0,
            0,
            0,
            0,
            0,
            1
          ],
          [
            0,
            0,
            0,
            0,
            0,
            1
          ],
          [
            0,
            0,
            0,
            0,
            0,
            0
          ],
          [
            0,
            0,
            0,
            0,
            0,
            0
          ]
        ]
      },
      "shot_map_available": true,
      "wikidata_id": "Q51093880",
      "name_cn_source": "wikidata"
    },
    {
      "name": "塞巴斯蒂安诺·卢佩尔托",
      "english_name": "Sebastiano Luperto",
      "position": "后卫",
      "age": 0,
      "nationality": "",
      "transfer_status": "current",
      "join_date": "",
      "contract_until": "",
      "market_value": 0,
      "stats": {
        "appearances": 31,
        "minutes": 2758,
        "goals": 1,
        "assists": 1,
        "yellow_cards": 4,
        "red_cards": 0
      },
      "shooting_stats": {
        "source": "understat",
        "shots": 10,
        "goals": 1,
        "xg": 0.9160170834511518,
        "npxg": 0.9160170834511518,
        "xg_chain": 4.817994193173945,
        "xg_buildup": 4.4588395189493895
      },
      "passing_stats": {
        "source": "understat",
        "key_passes": 5,
        "xa": 1.2335023880004883
      },
      "advanced_stats": {
        "source": "understat",
        "games": 31,
        "minutes": 2758,
        "position_code": "D",
        "xg": 0.9160170834511518,
        "xa": 1.2335023880004883,
        "npxg": 0.9160170834511518,
        "shots": 10,
        "key_passes": 5,
        "xg_chain": 4.817994193173945,
        "xg_buildup": 4.4588395189493895
      },
      "data_sources": [
        "sofascore.com",
        "understat.com"
      ],
      "understat_player_id": "1639",
      "heatmap": {
        "source": "understat_shots",
        "grid_rows": 5,
        "grid_cols": 6,
        "shot_count": 86,
        "shot_density": [
          [
            0,
            0,
            0,
            0,
            0,
            0
          ],
          [
            0,
            0,
            0,
            0,
            1,
            1
          ],
          [
            0,
            0,
            0,
            0,
            9,
            64
          ],
          [
            0,
            0,
            0,
            0,
            7,
            4
          ],
          [
            0,
            0,
            0,
            0,
            0,
            0
          ]
        ]
      },
      "shot_map_available": true,
      "wikidata_id": "Q19851177",
      "name_cn_source": "wikidata",
      "sofascore_player_id": 352736,
      "shirt_number": 5,
      "shirt_number_source": "sofascore"
    },
    {
      "name": "弗蘭科·巴斯克斯",
      "english_name": "Franco Vázquez",
      "position": "前锋",
      "age": 0,
      "nationality": "",
      "transfer_status": "current",
      "join_date": "",
      "contract_until": "",
      "market_value": 0,
      "stats": {
        "appearances": 15,
        "minutes": 485,
        "goals": 1,
        "assists": 1,
        "yellow_cards": 1,
        "red_cards": 0
      },
      "shooting_stats": {
        "source": "understat",
        "shots": 12,
        "goals": 1,
        "xg": 1.4491588799282908,
        "npxg": 1.4491588799282908,
        "xg_chain": 3.0313472282141447,
        "xg_buildup": 1.5376330390572548
      },
      "passing_stats": {
        "source": "understat",
        "key_passes": 9,
        "xa": 1.8917765356600285
      },
      "advanced_stats": {
        "source": "understat",
        "games": 15,
        "minutes": 485,
        "position_code": "F M S",
        "xg": 1.4491588799282908,
        "xa": 1.8917765356600285,
        "npxg": 1.4491588799282908,
        "shots": 12,
        "key_passes": 9,
        "xg_chain": 3.0313472282141447,
        "xg_buildup": 1.5376330390572548
      },
      "data_sources": [
        "understat.com"
      ],
      "understat_player_id": "1836",
      "heatmap": {
        "source": "understat_shots",
        "grid_rows": 5,
        "grid_cols": 6,
        "shot_count": 389,
        "shot_density": [
          [
            0,
            0,
            0,
            0,
            1,
            1
          ],
          [
            0,
            0,
            0,
            0,
            37,
            46
          ],
          [
            0,
            0,
            0,
            0,
            95,
            107
          ],
          [
            0,
            0,
            0,
            0,
            46,
            56
          ],
          [
            0,
            0,
            0,
            0,
            0,
            0
          ]
        ]
      },
      "shot_map_available": true,
      "wikidata_id": "Q2642101",
      "name_cn_source": "wikidata"
    },
    {
      "name": "辛拿比亞",
      "english_name": "Antonio Sanabria",
      "position": "前锋",
      "age": 0,
      "nationality": "",
      "transfer_status": "current",
      "join_date": "",
      "contract_until": "",
      "market_value": 0,
      "stats": {
        "appearances": 24,
        "minutes": 904,
        "goals": 1,
        "assists": 1,
        "yellow_cards": 2,
        "red_cards": 0
      },
      "shooting_stats": {
        "source": "understat",
        "shots": 12,
        "goals": 1,
        "xg": 2.979946978390217,
        "npxg": 2.979946978390217,
        "xg_chain": 3.9699571561068296,
        "xg_buildup": 0.3716926481574774
      },
      "passing_stats": {
        "source": "understat",
        "key_passes": 6,
        "xa": 1.9838042967021465
      },
      "advanced_stats": {
        "source": "understat",
        "games": 24,
        "minutes": 904,
        "position_code": "F S",
        "xg": 2.979946978390217,
        "xa": 1.9838042967021465,
        "npxg": 2.979946978390217,
        "shots": 12,
        "key_passes": 6,
        "xg_chain": 3.9699571561068296,
        "xg_buildup": 0.3716926481574774
      },
      "data_sources": [
        "sofascore.com",
        "understat.com"
      ],
      "understat_player_id": "2217",
      "heatmap": {
        "source": "understat_shots",
        "grid_rows": 5,
        "grid_cols": 6,
        "shot_count": 449,
        "shot_density": [
          [
            0,
            0,
            0,
            0,
            1,
            0
          ],
          [
            0,
            0,
            0,
            0,
            13,
            52
          ],
          [
            0,
            0,
            0,
            1,
            47,
            270
          ],
          [
            0,
            0,
            1,
            0,
            17,
            47
          ],
          [
            0,
            0,
            0,
            0,
            0,
            0
          ]
        ]
      },
      "shot_map_available": true,
      "wikidata_id": "Q10856523",
      "name_cn_source": "wikidata",
      "sofascore_player_id": 333261,
      "shirt_number": 99,
      "shirt_number_source": "sofascore"
    },
    {
      "name": "丹尼斯·強森",
      "english_name": "Dennis Johnsen",
      "position": "前锋",
      "age": 0,
      "nationality": "",
      "transfer_status": "current",
      "join_date": "",
      "contract_until": "",
      "market_value": 0,
      "stats": {
        "appearances": 11,
        "minutes": 390,
        "goals": 1,
        "assists": 1,
        "yellow_cards": 0,
        "red_cards": 0
      },
      "shooting_stats": {
        "source": "understat",
        "shots": 5,
        "goals": 1,
        "xg": 0.736239617690444,
        "npxg": 0.736239617690444,
        "xg_chain": 1.291289635002613,
        "xg_buildup": 0.0665459930896759
      },
      "passing_stats": {
        "source": "understat",
        "key_passes": 4,
        "xa": 0.6198056861758232
      },
      "advanced_stats": {
        "source": "understat",
        "games": 11,
        "minutes": 390,
        "position_code": "F M S",
        "xg": 0.736239617690444,
        "xa": 0.6198056861758232,
        "npxg": 0.736239617690444,
        "shots": 5,
        "key_passes": 4,
        "xg_chain": 1.291289635002613,
        "xg_buildup": 0.0665459930896759
      },
      "data_sources": [
        "understat.com"
      ],
      "understat_player_id": "9882",
      "heatmap": {
        "source": "understat_shots",
        "grid_rows": 5,
        "grid_cols": 6,
        "shot_count": 20,
        "shot_density": [
          [
            0,
            0,
            0,
            0,
            0,
            0
          ],
          [
            0,
            0,
            0,
            0,
            1,
            2
          ],
          [
            0,
            0,
            0,
            0,
            2,
            6
          ],
          [
            0,
            0,
            0,
            0,
            3,
            6
          ],
          [
            0,
            0,
            0,
            0,
            0,
            0
          ]
        ]
      },
      "shot_map_available": true,
      "wikidata_id": "Q36005290",
      "name_cn_source": "wikidata"
    },
    {
      "name": "戴维·奥凯雷克",
      "english_name": "David Okereke",
      "position": "前锋",
      "age": 0,
      "nationality": "",
      "transfer_status": "current",
      "join_date": "",
      "contract_until": "",
      "market_value": 0,
      "stats": {
        "appearances": 8,
        "minutes": 352,
        "goals": 1,
        "assists": 0,
        "yellow_cards": 0,
        "red_cards": 0
      },
      "shooting_stats": {
        "source": "understat",
        "shots": 6,
        "goals": 1,
        "xg": 0.6186391320079565,
        "npxg": 0.6186391320079565,
        "xg_chain": 1.0619242694228888,
        "xg_buildup": 0.5185244809836149
      },
      "passing_stats": {
        "source": "understat",
        "key_passes": 3,
        "xa": 0.42117523308843374
      },
      "advanced_stats": {
        "source": "understat",
        "games": 8,
        "minutes": 352,
        "position_code": "F S",
        "xg": 0.6186391320079565,
        "xa": 0.42117523308843374,
        "npxg": 0.6186391320079565,
        "shots": 6,
        "key_passes": 3,
        "xg_chain": 1.0619242694228888,
        "xg_buildup": 0.5185244809836149
      },
      "data_sources": [
        "sofascore.com",
        "understat.com"
      ],
      "understat_player_id": "9905",
      "heatmap": {
        "source": "understat_shots",
        "grid_rows": 5,
        "grid_cols": 6,
        "shot_count": 115,
        "shot_density": [
          [
            0,
            0,
            0,
            0,
            0,
            0
          ],
          [
            0,
            0,
            0,
            0,
            3,
            7
          ],
          [
            0,
            0,
            0,
            0,
            12,
            51
          ],
          [
            0,
            0,
            0,
            0,
            19,
            22
          ],
          [
            0,
            0,
            0,
            0,
            1,
            0
          ]
        ]
      },
      "shot_map_available": true,
      "wikidata_id": "Q28973641",
      "name_cn_source": "wikidata",
      "sofascore_player_id": 831290,
      "shirt_number": 77,
      "shirt_number_source": "sofascore"
    },
    {
      "name": "馬丁·帕耶羅",
      "english_name": "Martín Payero",
      "position": "中场",
      "age": 0,
      "nationality": "",
      "transfer_status": "current",
      "join_date": "",
      "contract_until": "",
      "market_value": 0,
      "stats": {
        "appearances": 25,
        "minutes": 1469,
        "goals": 1,
        "assists": 0,
        "yellow_cards": 8,
        "red_cards": 0
      },
      "shooting_stats": {
        "source": "understat",
        "shots": 23,
        "goals": 1,
        "xg": 1.4321895614266396,
        "npxg": 1.4321895614266396,
        "xg_chain": 3.3215508349239826,
        "xg_buildup": 2.247837715782225
      },
      "passing_stats": {
        "source": "understat",
        "key_passes": 13,
        "xa": 0.5584035962820053
      },
      "advanced_stats": {
        "source": "understat",
        "games": 25,
        "minutes": 1469,
        "position_code": "M S",
        "xg": 1.4321895614266396,
        "xa": 0.5584035962820053,
        "npxg": 1.4321895614266396,
        "shots": 23,
        "key_passes": 13,
        "xg_chain": 3.3215508349239826,
        "xg_buildup": 2.247837715782225
      },
      "data_sources": [
        "sofascore.com",
        "understat.com"
      ],
      "understat_player_id": "12084",
      "heatmap": {
        "source": "understat_shots",
        "grid_rows": 5,
        "grid_cols": 6,
        "shot_count": 92,
        "shot_density": [
          [
            0,
            0,
            0,
            0,
            0,
            0
          ],
          [
            0,
            0,
            0,
            0,
            9,
            6
          ],
          [
            0,
            0,
            0,
            0,
            35,
            14
          ],
          [
            0,
            0,
            0,
            0,
            17,
            9
          ],
          [
            0,
            0,
            0,
            0,
            1,
            1
          ]
        ]
      },
      "shot_map_available": true,
      "wikidata_id": "Q55281064",
      "name_cn_source": "wikidata",
      "sofascore_player_id": 895592,
      "shirt_number": 32,
      "shirt_number_source": "sofascore"
    },
    {
      "name": "傑瑞·范德普特",
      "english_name": "Jari Vandeputte",
      "position": "中场",
      "age": 0,
      "nationality": "",
      "transfer_status": "current",
      "join_date": "",
      "contract_until": "",
      "market_value": 0,
      "stats": {
        "appearances": 29,
        "minutes": 1823,
        "goals": 1,
        "assists": 4,
        "yellow_cards": 2,
        "red_cards": 0
      },
      "shooting_stats": {
        "source": "understat",
        "shots": 19,
        "goals": 1,
        "xg": 1.9982239250093699,
        "npxg": 1.9982239250093699,
        "xg_chain": 6.660647621378303,
        "xg_buildup": 4.049240369349718
      },
      "passing_stats": {
        "source": "understat",
        "key_passes": 50,
        "xa": 5.302346043288708
      },
      "advanced_stats": {
        "source": "understat",
        "games": 29,
        "minutes": 1823,
        "position_code": "M S",
        "xg": 1.9982239250093699,
        "xa": 5.302346043288708,
        "npxg": 1.9982239250093699,
        "shots": 19,
        "key_passes": 50,
        "xg_chain": 6.660647621378303,
        "xg_buildup": 4.049240369349718
      },
      "data_sources": [
        "sofascore.com",
        "understat.com"
      ],
      "understat_player_id": "13898",
      "heatmap": {
        "source": "understat_shots",
        "grid_rows": 5,
        "grid_cols": 6,
        "shot_count": 19,
        "shot_density": [
          [
            0,
            0,
            0,
            0,
            0,
            0
          ],
          [
            0,
            0,
            0,
            0,
            2,
            0
          ],
          [
            0,
            0,
            0,
            0,
            5,
            4
          ],
          [
            0,
            0,
            0,
            0,
            5,
            3
          ],
          [
            0,
            0,
            0,
            0,
            0,
            0
          ]
        ]
      },
      "shot_map_available": true,
      "wikidata_id": "Q14325154",
      "name_cn_source": "wikidata",
      "sofascore_player_id": 318645,
      "shirt_number": 27,
      "shirt_number_source": "sofascore"
    },
    {
      "name": "Francesco Folino",
      "english_name": "Francesco Folino",
      "position": "后卫",
      "age": 0,
      "nationality": "",
      "transfer_status": "current",
      "join_date": "",
      "contract_until": "",
      "market_value": 0,
      "stats": {
        "appearances": 17,
        "minutes": 686,
        "goals": 1,
        "assists": 0,
        "yellow_cards": 0,
        "red_cards": 0
      },
      "shooting_stats": {
        "source": "understat",
        "shots": 2,
        "goals": 1,
        "xg": 0.3679794892668724,
        "npxg": 0.3679794892668724,
        "xg_chain": 0.8554316479712725,
        "xg_buildup": 0.8554316479712725
      },
      "passing_stats": {
        "source": "understat",
        "key_passes": 1,
        "xa": 0.016072319820523262
      },
      "advanced_stats": {
        "source": "understat",
        "games": 17,
        "minutes": 686,
        "position_code": "D S",
        "xg": 0.3679794892668724,
        "xa": 0.016072319820523262,
        "npxg": 0.3679794892668724,
        "shots": 2,
        "key_passes": 1,
        "xg_chain": 0.8554316479712725,
        "xg_buildup": 0.8554316479712725
      },
      "data_sources": [
        "sofascore.com",
        "understat.com"
      ],
      "understat_player_id": "13901",
      "heatmap": {
        "source": "understat_shots",
        "grid_rows": 5,
        "grid_cols": 6,
        "shot_count": 2,
        "shot_density": [
          [
            0,
            0,
            0,
            0,
            0,
            0
          ],
          [
            0,
            0,
            0,
            0,
            0,
            0
          ],
          [
            0,
            0,
            0,
            0,
            0,
            2
          ],
          [
            0,
            0,
            0,
            0,
            0,
            0
          ],
          [
            0,
            0,
            0,
            0,
            0,
            0
          ]
        ]
      },
      "shot_map_available": true,
      "wikidata_id": "Q135424787",
      "name_cn_source": "wikidata",
      "sofascore_player_id": 1424353,
      "shirt_number": 55,
      "shirt_number_source": "sofascore"
    },
    {
      "name": "朱塞佩·佩澤拉",
      "english_name": "Giuseppe Pezzella",
      "position": "后卫",
      "age": 0,
      "nationality": "",
      "transfer_status": "current",
      "join_date": "",
      "contract_until": "",
      "market_value": 0,
      "stats": {
        "appearances": 28,
        "minutes": 2359,
        "goals": 0,
        "assists": 1,
        "yellow_cards": 8,
        "red_cards": 1
      },
      "shooting_stats": {
        "source": "understat",
        "shots": 5,
        "goals": 0,
        "xg": 0.10538806114345789,
        "npxg": 0.10538806114345789,
        "xg_chain": 4.757028068415821,
        "xg_buildup": 3.5445721400901675
      },
      "passing_stats": {
        "source": "understat",
        "key_passes": 26,
        "xa": 1.5860623018816113
      },
      "advanced_stats": {
        "source": "understat",
        "games": 28,
        "minutes": 2359,
        "position_code": "D M S",
        "xg": 0.10538806114345789,
        "xa": 1.5860623018816113,
        "npxg": 0.10538806114345789,
        "shots": 5,
        "key_passes": 26,
        "xg_chain": 4.757028068415821,
        "xg_buildup": 3.5445721400901675
      },
      "data_sources": [
        "sofascore.com",
        "understat.com"
      ],
      "understat_player_id": "1281",
      "heatmap": {
        "source": "understat_shots",
        "grid_rows": 5,
        "grid_cols": 6,
        "shot_count": 61,
        "shot_density": [
          [
            0,
            0,
            0,
            0,
            0,
            0
          ],
          [
            0,
            0,
            0,
            0,
            2,
            0
          ],
          [
            0,
            0,
            0,
            0,
            11,
            3
          ],
          [
            0,
            0,
            0,
            0,
            21,
            24
          ],
          [
            0,
            0,
            0,
            0,
            0,
            0
          ]
        ]
      },
      "shot_map_available": true,
      "wikidata_id": "Q22991777",
      "name_cn_source": "wikidata",
      "sofascore_player_id": 814589,
      "shirt_number": 3,
      "shirt_number_source": "sofascore"
    },
    {
      "name": "埃米利奥·奥德罗",
      "english_name": "Emil Audero",
      "position": "门将",
      "age": 0,
      "nationality": "",
      "transfer_status": "current",
      "join_date": "",
      "contract_until": "",
      "market_value": 0,
      "stats": {
        "appearances": 31,
        "minutes": 2790,
        "goals": 0,
        "assists": 0,
        "yellow_cards": 0,
        "red_cards": 0
      },
      "shooting_stats": {
        "source": "understat",
        "shots": 0,
        "goals": 0,
        "xg": 0.0,
        "npxg": 0.0,
        "xg_chain": 0.8675176659598947,
        "xg_buildup": 0.8675176659598947
      },
      "passing_stats": {
        "source": "understat",
        "key_passes": 0,
        "xa": 0.0
      },
      "advanced_stats": {
        "source": "understat",
        "games": 31,
        "minutes": 2790,
        "position_code": "GK",
        "xg": 0.0,
        "xa": 0.0,
        "npxg": 0.0,
        "shots": 0,
        "key_passes": 0,
        "xg_chain": 0.8675176659598947,
        "xg_buildup": 0.8675176659598947
      },
      "data_sources": [
        "sofascore.com",
        "understat.com"
      ],
      "understat_player_id": "1302",
      "wikidata_id": "Q17410409",
      "name_cn_source": "wikidata",
      "sofascore_player_id": 318603,
      "shirt_number": 1,
      "shirt_number_source": "sofascore"
    },
    {
      "name": "费代里科·切凯里尼",
      "english_name": "Federico Ceccherini",
      "position": "后卫",
      "age": 0,
      "nationality": "",
      "transfer_status": "current",
      "join_date": "",
      "contract_until": "",
      "market_value": 0,
      "stats": {
        "appearances": 9,
        "minutes": 475,
        "goals": 0,
        "assists": 1,
        "yellow_cards": 1,
        "red_cards": 1
      },
      "shooting_stats": {
        "source": "understat",
        "shots": 5,
        "goals": 0,
        "xg": 0.19045374542474747,
        "npxg": 0.19045374542474747,
        "xg_chain": 0.7198278941214085,
        "xg_buildup": 0.6481388285756111
      },
      "passing_stats": {
        "source": "understat",
        "key_passes": 2,
        "xa": 0.41685381904244423
      },
      "advanced_stats": {
        "source": "understat",
        "games": 9,
        "minutes": 475,
        "position_code": "D S",
        "xg": 0.19045374542474747,
        "xa": 0.41685381904244423,
        "npxg": 0.19045374542474747,
        "shots": 5,
        "key_passes": 2,
        "xg_chain": 0.7198278941214085,
        "xg_buildup": 0.6481388285756111
      },
      "data_sources": [
        "sofascore.com",
        "understat.com"
      ],
      "understat_player_id": "1370",
      "heatmap": {
        "source": "understat_shots",
        "grid_rows": 5,
        "grid_cols": 6,
        "shot_count": 72,
        "shot_density": [
          [
            0,
            0,
            0,
            0,
            0,
            0
          ],
          [
            0,
            0,
            1,
            0,
            3,
            8
          ],
          [
            1,
            0,
            0,
            0,
            7,
            38
          ],
          [
            0,
            0,
            0,
            0,
            2,
            10
          ],
          [
            0,
            0,
            0,
            1,
            1,
            0
          ]
        ]
      },
      "shot_map_available": true,
      "wikidata_id": "Q5605391",
      "name_cn_source": "wikidata",
      "sofascore_player_id": 139410,
      "shirt_number": 23,
      "shirt_number_source": "sofascore"
    },
    {
      "name": "阿爾貝托·格拉西",
      "english_name": "Alberto Grassi",
      "position": "中场",
      "age": 0,
      "nationality": "",
      "transfer_status": "current",
      "join_date": "",
      "contract_until": "",
      "market_value": 0,
      "stats": {
        "appearances": 27,
        "minutes": 1502,
        "goals": 0,
        "assists": 0,
        "yellow_cards": 3,
        "red_cards": 0
      },
      "shooting_stats": {
        "source": "understat",
        "shots": 10,
        "goals": 0,
        "xg": 0.6888829646632075,
        "npxg": 0.6888829646632075,
        "xg_chain": 3.4094439232721925,
        "xg_buildup": 2.475841867737472
      },
      "passing_stats": {
        "source": "understat",
        "key_passes": 7,
        "xa": 0.407305583357811
      },
      "advanced_stats": {
        "source": "understat",
        "games": 27,
        "minutes": 1502,
        "position_code": "M S",
        "xg": 0.6888829646632075,
        "xa": 0.407305583357811,
        "npxg": 0.6888829646632075,
        "shots": 10,
        "key_passes": 7,
        "xg_chain": 3.4094439232721925,
        "xg_buildup": 2.475841867737472
      },
      "data_sources": [
        "sofascore.com",
        "understat.com"
      ],
      "understat_player_id": "1504",
      "heatmap": {
        "source": "understat_shots",
        "grid_rows": 5,
        "grid_cols": 6,
        "shot_count": 172,
        "shot_density": [
          [
            0,
            0,
            0,
            0,
            0,
            0
          ],
          [
            0,
            0,
            0,
            0,
            17,
            18
          ],
          [
            2,
            0,
            0,
            0,
            45,
            65
          ],
          [
            0,
            0,
            0,
            2,
            14,
            8
          ],
          [
            0,
            0,
            0,
            0,
            0,
            1
          ]
        ]
      },
      "shot_map_available": true,
      "wikidata_id": "Q18637410",
      "name_cn_source": "wikidata",
      "sofascore_player_id": 186845,
      "shirt_number": 33,
      "shirt_number_source": "sofascore"
    },
    {
      "name": "馬特奧·比安凱蒂",
      "english_name": "Matteo Bianchetti",
      "position": "后卫",
      "age": 0,
      "nationality": "",
      "transfer_status": "current",
      "join_date": "",
      "contract_until": "",
      "market_value": 0,
      "stats": {
        "appearances": 24,
        "minutes": 1952,
        "goals": 0,
        "assists": 2,
        "yellow_cards": 3,
        "red_cards": 0
      },
      "shooting_stats": {
        "source": "understat",
        "shots": 6,
        "goals": 0,
        "xg": 0.34063241444528103,
        "npxg": 0.34063241444528103,
        "xg_chain": 3.172197064384818,
        "xg_buildup": 2.869701823219657
      },
      "passing_stats": {
        "source": "understat",
        "key_passes": 4,
        "xa": 0.48775646602734923
      },
      "advanced_stats": {
        "source": "understat",
        "games": 24,
        "minutes": 1952,
        "position_code": "D S",
        "xg": 0.34063241444528103,
        "xa": 0.48775646602734923,
        "npxg": 0.34063241444528103,
        "shots": 6,
        "key_passes": 4,
        "xg_chain": 3.172197064384818,
        "xg_buildup": 2.869701823219657
      },
      "data_sources": [
        "sofascore.com",
        "understat.com"
      ],
      "understat_player_id": "1843",
      "heatmap": {
        "source": "understat_shots",
        "grid_rows": 5,
        "grid_cols": 6,
        "shot_count": 20,
        "shot_density": [
          [
            0,
            0,
            0,
            0,
            0,
            0
          ],
          [
            0,
            0,
            0,
            0,
            1,
            1
          ],
          [
            0,
            0,
            0,
            0,
            1,
            15
          ],
          [
            0,
            0,
            0,
            0,
            0,
            2
          ],
          [
            0,
            0,
            0,
            0,
            0,
            0
          ]
        ]
      },
      "shot_map_available": true,
      "wikidata_id": "Q6789649",
      "name_cn_source": "wikidata",
      "sofascore_player_id": 158037,
      "shirt_number": 15,
      "shirt_number_source": "sofascore"
    },
    {
      "name": "阿莱西奥·泽尔宾",
      "english_name": "Alessio Zerbin",
      "position": "后卫",
      "age": 0,
      "nationality": "",
      "transfer_status": "current",
      "join_date": "",
      "contract_until": "",
      "market_value": 0,
      "stats": {
        "appearances": 30,
        "minutes": 1562,
        "goals": 0,
        "assists": 2,
        "yellow_cards": 1,
        "red_cards": 0
      },
      "shooting_stats": {
        "source": "understat",
        "shots": 21,
        "goals": 0,
        "xg": 1.82145987264812,
        "npxg": 1.82145987264812,
        "xg_chain": 5.096774972975254,
        "xg_buildup": 1.93684624414891
      },
      "passing_stats": {
        "source": "understat",
        "key_passes": 16,
        "xa": 2.449772959575057
      },
      "advanced_stats": {
        "source": "understat",
        "games": 30,
        "minutes": 1562,
        "position_code": "D M S",
        "xg": 1.82145987264812,
        "xa": 2.449772959575057,
        "npxg": 1.82145987264812,
        "shots": 21,
        "key_passes": 16,
        "xg_chain": 5.096774972975254,
        "xg_buildup": 1.93684624414891
      },
      "data_sources": [
        "sofascore.com",
        "understat.com"
      ],
      "understat_player_id": "4911",
      "heatmap": {
        "source": "understat_shots",
        "grid_rows": 5,
        "grid_cols": 6,
        "shot_count": 52,
        "shot_density": [
          [
            0,
            0,
            0,
            0,
            0,
            0
          ],
          [
            0,
            0,
            0,
            0,
            5,
            15
          ],
          [
            0,
            0,
            0,
            0,
            11,
            15
          ],
          [
            0,
            0,
            0,
            0,
            2,
            4
          ],
          [
            0,
            0,
            0,
            0,
            0,
            0
          ]
        ]
      },
      "shot_map_available": true,
      "wikidata_id": "Q60734883",
      "name_cn_source": "wikidata",
      "sofascore_player_id": 869888,
      "shirt_number": 7,
      "shirt_number_source": "sofascore"
    },
    {
      "name": "馬爾科·西爾維斯特里",
      "english_name": "Marco Silvestri",
      "position": "门将",
      "age": 0,
      "nationality": "",
      "transfer_status": "current",
      "join_date": "",
      "contract_until": "",
      "market_value": 0,
      "stats": {
        "appearances": 4,
        "minutes": 360,
        "goals": 0,
        "assists": 0,
        "yellow_cards": 0,
        "red_cards": 0
      },
      "shooting_stats": {
        "source": "understat",
        "shots": 0,
        "goals": 0,
        "xg": 0.0,
        "npxg": 0.0,
        "xg_chain": 0.03316120430827141,
        "xg_buildup": 0.03316120430827141
      },
      "passing_stats": {
        "source": "understat",
        "key_passes": 0,
        "xa": 0.0
      },
      "advanced_stats": {
        "source": "understat",
        "games": 4,
        "minutes": 360,
        "position_code": "GK",
        "xg": 0.0,
        "xa": 0.0,
        "npxg": 0.0,
        "shots": 0,
        "key_passes": 0,
        "xg_chain": 0.03316120430827141,
        "xg_buildup": 0.03316120430827141
      },
      "data_sources": [
        "sofascore.com",
        "understat.com"
      ],
      "understat_player_id": "6132",
      "wikidata_id": "Q6757717",
      "name_cn_source": "wikidata",
      "sofascore_player_id": 43970,
      "shirt_number": 16,
      "shirt_number_source": "sofascore"
    },
    {
      "name": "杰里米·萨缅托",
      "english_name": "Jeremy Sarmiento",
      "position": "",
      "age": 0,
      "nationality": "",
      "transfer_status": "current",
      "join_date": "",
      "contract_until": "",
      "market_value": 0,
      "stats": {
        "appearances": 7,
        "minutes": 127,
        "goals": 0,
        "assists": 0,
        "yellow_cards": 0,
        "red_cards": 0
      },
      "shooting_stats": {
        "source": "understat",
        "shots": 2,
        "goals": 0,
        "xg": 0.05533710680902004,
        "npxg": 0.05533710680902004,
        "xg_chain": 0.5485026314854622,
        "xg_buildup": 0.3956798752769828
      },
      "passing_stats": {
        "source": "understat",
        "key_passes": 3,
        "xa": 0.1608402132987976
      },
      "advanced_stats": {
        "source": "understat",
        "games": 7,
        "minutes": 127,
        "position_code": "S",
        "xg": 0.05533710680902004,
        "xa": 0.1608402132987976,
        "npxg": 0.05533710680902004,
        "shots": 2,
        "key_passes": 3,
        "xg_chain": 0.5485026314854622,
        "xg_buildup": 0.3956798752769828
      },
      "data_sources": [
        "understat.com"
      ],
      "understat_player_id": "10036",
      "heatmap": {
        "source": "understat_shots",
        "grid_rows": 5,
        "grid_cols": 6,
        "shot_count": 7,
        "shot_density": [
          [
            0,
            0,
            0,
            0,
            0,
            0
          ],
          [
            0,
            0,
            0,
            0,
            0,
            0
          ],
          [
            0,
            0,
            0,
            0,
            4,
            2
          ],
          [
            0,
            0,
            0,
            0,
            0,
            1
          ],
          [
            0,
            0,
            0,
            0,
            0,
            0
          ]
        ]
      },
      "shot_map_available": true,
      "wikidata_id": "Q108659564",
      "name_cn_source": "wikidata"
    },
    {
      "name": "罗曼诺·贝尼托·弗洛里亚尼·墨索里尼",
      "english_name": "Romano Floriani",
      "position": "后卫",
      "age": 0,
      "nationality": "",
      "transfer_status": "current",
      "join_date": "",
      "contract_until": "",
      "market_value": 0,
      "stats": {
        "appearances": 26,
        "minutes": 1089,
        "goals": 0,
        "assists": 1,
        "yellow_cards": 2,
        "red_cards": 0
      },
      "shooting_stats": {
        "source": "understat",
        "shots": 5,
        "goals": 0,
        "xg": 0.20024864189326763,
        "npxg": 0.20024864189326763,
        "xg_chain": 1.9743683747947216,
        "xg_buildup": 1.198974552564323
      },
      "passing_stats": {
        "source": "understat",
        "key_passes": 9,
        "xa": 1.3022935949265957
      },
      "advanced_stats": {
        "source": "understat",
        "games": 26,
        "minutes": 1089,
        "position_code": "D M S",
        "xg": 0.20024864189326763,
        "xa": 1.3022935949265957,
        "npxg": 0.20024864189326763,
        "shots": 5,
        "key_passes": 9,
        "xg_chain": 1.9743683747947216,
        "xg_buildup": 1.198974552564323
      },
      "data_sources": [
        "understat.com"
      ],
      "understat_player_id": "10075",
      "heatmap": {
        "source": "understat_shots",
        "grid_rows": 5,
        "grid_cols": 6,
        "shot_count": 5,
        "shot_density": [
          [
            0,
            0,
            0,
            0,
            0,
            0
          ],
          [
            0,
            0,
            0,
            0,
            0,
            0
          ],
          [
            0,
            0,
            0,
            0,
            2,
            2
          ],
          [
            0,
            0,
            0,
            0,
            1,
            0
          ],
          [
            0,
            0,
            0,
            0,
            0,
            0
          ]
        ]
      },
      "shot_map_available": true,
      "wikidata_id": "Q105268643",
      "name_cn_source": "wikidata"
    },
    {
      "name": "Warren Bondo",
      "english_name": "Warren Bondo",
      "position": "中场",
      "age": 0,
      "nationality": "",
      "transfer_status": "current",
      "join_date": "",
      "contract_until": "",
      "market_value": 0,
      "stats": {
        "appearances": 27,
        "minutes": 1788,
        "goals": 0,
        "assists": 0,
        "yellow_cards": 5,
        "red_cards": 0
      },
      "shooting_stats": {
        "source": "understat",
        "shots": 8,
        "goals": 0,
        "xg": 0.2856207136064768,
        "npxg": 0.2856207136064768,
        "xg_chain": 3.443341282196343,
        "xg_buildup": 2.995934301055968
      },
      "passing_stats": {
        "source": "understat",
        "key_passes": 3,
        "xa": 0.161786250770092
      },
      "advanced_stats": {
        "source": "understat",
        "games": 27,
        "minutes": 1788,
        "position_code": "M S",
        "xg": 0.2856207136064768,
        "xa": 0.161786250770092,
        "npxg": 0.2856207136064768,
        "shots": 8,
        "key_passes": 3,
        "xg_chain": 3.443341282196343,
        "xg_buildup": 2.995934301055968
      },
      "data_sources": [
        "sofascore.com",
        "understat.com"
      ],
      "understat_player_id": "10898",
      "heatmap": {
        "source": "understat_shots",
        "grid_rows": 5,
        "grid_cols": 6,
        "shot_count": 40,
        "shot_density": [
          [
            0,
            0,
            0,
            0,
            0,
            0
          ],
          [
            0,
            0,
            0,
            0,
            8,
            2
          ],
          [
            0,
            0,
            0,
            0,
            18,
            5
          ],
          [
            0,
            0,
            0,
            0,
            3,
            4
          ],
          [
            0,
            0,
            0,
            0,
            0,
            0
          ]
        ]
      },
      "shot_map_available": true,
      "wikidata_id": "Q103232786",
      "name_cn_source": "wikidata",
      "sofascore_player_id": 1000366,
      "shirt_number": 38,
      "shirt_number_source": "sofascore"
    },
    {
      "name": "Tommaso Barbieri",
      "english_name": "Tommaso Barbieri",
      "position": "后卫",
      "age": 0,
      "nationality": "",
      "transfer_status": "current",
      "join_date": "",
      "contract_until": "",
      "market_value": 0,
      "stats": {
        "appearances": 26,
        "minutes": 1542,
        "goals": 0,
        "assists": 1,
        "yellow_cards": 7,
        "red_cards": 0
      },
      "shooting_stats": {
        "source": "understat",
        "shots": 14,
        "goals": 0,
        "xg": 0.8731019468978047,
        "npxg": 0.8731019468978047,
        "xg_chain": 4.836792923510075,
        "xg_buildup": 2.182511310093105
      },
      "passing_stats": {
        "source": "understat",
        "key_passes": 10,
        "xa": 1.8337322100996971
      },
      "advanced_stats": {
        "source": "understat",
        "games": 26,
        "minutes": 1542,
        "position_code": "D M S",
        "xg": 0.8731019468978047,
        "xa": 1.8337322100996971,
        "npxg": 0.8731019468978047,
        "shots": 14,
        "key_passes": 10,
        "xg_chain": 4.836792923510075,
        "xg_buildup": 2.182511310093105
      },
      "data_sources": [
        "sofascore.com",
        "understat.com"
      ],
      "understat_player_id": "11139",
      "heatmap": {
        "source": "understat_shots",
        "grid_rows": 5,
        "grid_cols": 6,
        "shot_count": 14,
        "shot_density": [
          [
            0,
            0,
            0,
            0,
            0,
            0
          ],
          [
            0,
            0,
            0,
            0,
            3,
            4
          ],
          [
            0,
            0,
            0,
            0,
            2,
            2
          ],
          [
            0,
            0,
            0,
            0,
            1,
            1
          ],
          [
            0,
            0,
            0,
            0,
            0,
            1
          ]
        ]
      },
      "shot_map_available": true,
      "wikidata_id": "Q74667734",
      "name_cn_source": "wikidata",
      "sofascore_player_id": 993389,
      "shirt_number": 4,
      "shirt_number_source": "sofascore"
    },
    {
      "name": "Faris Pemi Moumbagna",
      "english_name": "Faris Moumbagna",
      "position": "前锋",
      "age": 0,
      "nationality": "",
      "transfer_status": "current",
      "join_date": "",
      "contract_until": "",
      "market_value": 0,
      "stats": {
        "appearances": 5,
        "minutes": 72,
        "goals": 0,
        "assists": 0,
        "yellow_cards": 0,
        "red_cards": 0
      },
      "shooting_stats": {
        "source": "understat",
        "shots": 2,
        "goals": 0,
        "xg": 0.4495754614472389,
        "npxg": 0.4495754614472389,
        "xg_chain": 0.4004152715206146,
        "xg_buildup": 0.0
      },
      "passing_stats": {
        "source": "understat",
        "key_passes": 1,
        "xa": 0.017842786386609077
      },
      "advanced_stats": {
        "source": "understat",
        "games": 5,
        "minutes": 72,
        "position_code": "S",
        "xg": 0.4495754614472389,
        "xa": 0.017842786386609077,
        "npxg": 0.4495754614472389,
        "shots": 2,
        "key_passes": 1,
        "xg_chain": 0.4004152715206146,
        "xg_buildup": 0.0
      },
      "data_sources": [
        "sofascore.com",
        "understat.com"
      ],
      "understat_player_id": "12425",
      "heatmap": {
        "source": "understat_shots",
        "grid_rows": 5,
        "grid_cols": 6,
        "shot_count": 18,
        "shot_density": [
          [
            0,
            0,
            0,
            0,
            0,
            0
          ],
          [
            0,
            0,
            0,
            0,
            0,
            2
          ],
          [
            0,
            0,
            0,
            0,
            2,
            13
          ],
          [
            0,
            0,
            0,
            0,
            0,
            1
          ],
          [
            0,
            0,
            0,
            0,
            0,
            0
          ]
        ]
      },
      "shot_map_available": true,
      "wikidata_id": "Q55820199",
      "name_cn_source": "wikidata",
      "sofascore_player_id": 1029456,
      "shirt_number": 14,
      "shirt_number_source": "sofascore"
    },
    {
      "name": "Mikayil Faye",
      "english_name": "Mikayil Faye",
      "position": "后卫",
      "age": 0,
      "nationality": "",
      "transfer_status": "current",
      "join_date": "",
      "contract_until": "",
      "market_value": 0,
      "stats": {
        "appearances": 8,
        "minutes": 238,
        "goals": 0,
        "assists": 0,
        "yellow_cards": 1,
        "red_cards": 0
      },
      "shooting_stats": {
        "source": "understat",
        "shots": 2,
        "goals": 0,
        "xg": 0.045254429802298546,
        "npxg": 0.045254429802298546,
        "xg_chain": 0.7969660088419914,
        "xg_buildup": 0.3307258803397417
      },
      "passing_stats": {
        "source": "understat",
        "key_passes": 1,
        "xa": 0.4483277201652527
      },
      "advanced_stats": {
        "source": "understat",
        "games": 8,
        "minutes": 238,
        "position_code": "D M S",
        "xg": 0.045254429802298546,
        "xa": 0.4483277201652527,
        "npxg": 0.045254429802298546,
        "shots": 2,
        "key_passes": 1,
        "xg_chain": 0.7969660088419914,
        "xg_buildup": 0.3307258803397417
      },
      "data_sources": [
        "sofascore.com",
        "understat.com"
      ],
      "understat_player_id": "12530",
      "heatmap": {
        "source": "understat_shots",
        "grid_rows": 5,
        "grid_cols": 6,
        "shot_count": 8,
        "shot_density": [
          [
            0,
            0,
            0,
            0,
            0,
            0
          ],
          [
            0,
            0,
            0,
            0,
            0,
            0
          ],
          [
            0,
            0,
            0,
            0,
            1,
            3
          ],
          [
            0,
            0,
            0,
            0,
            2,
            2
          ],
          [
            0,
            0,
            0,
            0,
            0,
            0
          ]
        ]
      },
      "shot_map_available": true,
      "wikidata_id": "Q119154039",
      "name_cn_source": "wikidata",
      "sofascore_player_id": 1002564,
      "shirt_number": 30,
      "shirt_number_source": "sofascore"
    },
    {
      "name": "科洛科洛（足球運動員）",
      "english_name": "Michele Collocolo",
      "position": "中场",
      "age": 0,
      "nationality": "",
      "transfer_status": "current",
      "join_date": "",
      "contract_until": "",
      "market_value": 0,
      "stats": {
        "appearances": 6,
        "minutes": 308,
        "goals": 0,
        "assists": 0,
        "yellow_cards": 1,
        "red_cards": 0
      },
      "shooting_stats": {
        "source": "understat",
        "shots": 2,
        "goals": 0,
        "xg": 0.07672501634806395,
        "npxg": 0.07672501634806395,
        "xg_chain": 0.25151657313108444,
        "xg_buildup": 0.03967037424445152
      },
      "passing_stats": {
        "source": "understat",
        "key_passes": 2,
        "xa": 0.1351211853325367
      },
      "advanced_stats": {
        "source": "understat",
        "games": 6,
        "minutes": 308,
        "position_code": "M S",
        "xg": 0.07672501634806395,
        "xa": 0.1351211853325367,
        "npxg": 0.07672501634806395,
        "shots": 2,
        "key_passes": 2,
        "xg_chain": 0.25151657313108444,
        "xg_buildup": 0.03967037424445152
      },
      "data_sources": [
        "sofascore.com",
        "understat.com"
      ],
      "understat_player_id": "13899",
      "heatmap": {
        "source": "understat_shots",
        "grid_rows": 5,
        "grid_cols": 6,
        "shot_count": 2,
        "shot_density": [
          [
            0,
            0,
            0,
            0,
            0,
            0
          ],
          [
            0,
            0,
            0,
            0,
            1,
            1
          ],
          [
            0,
            0,
            0,
            0,
            0,
            0
          ],
          [
            0,
            0,
            0,
            0,
            0,
            0
          ],
          [
            0,
            0,
            0,
            0,
            0,
            0
          ]
        ]
      },
      "shot_map_available": true,
      "wikidata_id": "Q109750111",
      "name_cn_source": "wikidata",
      "sofascore_player_id": 839925,
      "shirt_number": 18,
      "shirt_number_source": "sofascore"
    },
    {
      "name": "Dachi Lordkipanidze",
      "english_name": "Dachi Lordkipanidze",
      "position": "",
      "age": 0,
      "nationality": "",
      "transfer_status": "current",
      "join_date": "",
      "contract_until": "",
      "market_value": 0,
      "stats": {
        "appearances": 1,
        "minutes": 27,
        "goals": 0,
        "assists": 0,
        "yellow_cards": 0,
        "red_cards": 0
      },
      "shooting_stats": {
        "source": "understat",
        "shots": 0,
        "goals": 0,
        "xg": 0.0,
        "npxg": 0.0,
        "xg_chain": 0.0,
        "xg_buildup": 0.0
      },
      "passing_stats": {
        "source": "understat",
        "key_passes": 0,
        "xa": 0.0
      },
      "advanced_stats": {
        "source": "understat",
        "games": 1,
        "minutes": 27,
        "position_code": "S",
        "xg": 0.0,
        "xa": 0.0,
        "npxg": 0.0,
        "shots": 0,
        "key_passes": 0,
        "xg_chain": 0.0,
        "xg_buildup": 0.0
      },
      "data_sources": [
        "understat.com"
      ],
      "understat_player_id": "13900",
      "wikidata_id": "Q135424818",
      "name_cn_source": "wikidata"
    },
    {
      "name": "Milan Đurić",
      "english_name": "Milan Đurić",
      "position": "前锋",
      "age": 0,
      "nationality": "Bosnia & Herzegovina",
      "transfer_status": "current",
      "market_value": 0,
      "stats": {
        "appearances": 0,
        "minutes": 0,
        "goals": 0,
        "assists": 0,
        "yellow_cards": 0,
        "red_cards": 0
      },
      "data_sources": [
        "sofascore.com"
      ],
      "sofascore_player_id": 76132,
      "shirt_number": 9,
      "shirt_number_source": "sofascore"
    },
    {
      "name": "Romano Floriani Mussolini",
      "english_name": "Romano Floriani Mussolini",
      "position": "中场",
      "age": 0,
      "nationality": "Italy",
      "transfer_status": "current",
      "market_value": 0,
      "stats": {
        "appearances": 0,
        "minutes": 0,
        "goals": 0,
        "assists": 0,
        "yellow_cards": 0,
        "red_cards": 0
      },
      "data_sources": [
        "sofascore.com"
      ],
      "sofascore_player_id": 1100354,
      "shirt_number": 22,
      "shirt_number_source": "sofascore"
    },
    {
      "name": "Youssef Maleh",
      "english_name": "Youssef Maleh",
      "position": "中场",
      "age": 0,
      "nationality": "Morocco",
      "transfer_status": "current",
      "market_value": 0,
      "stats": {
        "appearances": 0,
        "minutes": 0,
        "goals": 0,
        "assists": 0,
        "yellow_cards": 0,
        "red_cards": 0
      },
      "data_sources": [
        "sofascore.com"
      ],
      "sofascore_player_id": 849274,
      "shirt_number": 29,
      "shirt_number_source": "sofascore"
    },
    {
      "name": "Morten Thorsby",
      "english_name": "Morten Thorsby",
      "position": "中场",
      "age": 0,
      "nationality": "Norway",
      "transfer_status": "current",
      "market_value": 0,
      "stats": {
        "appearances": 0,
        "minutes": 0,
        "goals": 0,
        "assists": 0,
        "yellow_cards": 0,
        "red_cards": 0
      },
      "data_sources": [
        "sofascore.com"
      ],
      "sofascore_player_id": 280991,
      "shirt_number": 2,
      "shirt_number_source": "sofascore"
    },
    {
      "name": "Lapo Nava",
      "english_name": "Lapo Nava",
      "position": "门将",
      "age": 0,
      "nationality": "Italy",
      "transfer_status": "current",
      "market_value": 0,
      "stats": {
        "appearances": 0,
        "minutes": 0,
        "goals": 0,
        "assists": 0,
        "yellow_cards": 0,
        "red_cards": 0
      },
      "data_sources": [
        "sofascore.com"
      ],
      "sofascore_player_id": 1141168,
      "shirt_number": 69,
      "shirt_number_source": "sofascore"
    }
  ],
  "last_updated": "Tue, 05 May 2026 14:32:42 GMT",
  "season": "2026"
}